examples/quickstart/quickstart.py
examples/quickstart/quickstart_batching.py
linq/__init__.py
linq/_internal/__init__.py
linq/_internal/client.py
linq/auth/__init__.py
linq/auth/client_auth.py
linq/auth/server.py
linq/cli/__init__.py
linq/cli/auth.py
linq/cli/cli_safe_linq_client.py
linq/cli/cli_safe_wrapper.py
linq/cli/driver.py
linq/cli/main.py
linq/cli/scripts.py
linq/cli/utils.py
linq/cli/workcell.py
linq/cli/workflow.py
linq/client.py
linq/config.py
linq/credentials.py
linq/drivers.py
linq/exceptions.py
linq/file_store.py
linq/hooks.py
linq/labware.py
linq/maestro_webhooks_temp.py
linq/parameters.py
linq/schema/__init__.py
linq/schema/auth_api.py
linq/schema/backend_api.py
linq/schema/workflow.py
linq/schema/workflow_api.py
linq/schema/workflow_api_types.py
linq/sdk_entity.py
linq/task.py
linq/task_factory.py
linq/types.py
linq/utils.py
linq/visualize.py
linq/workcell.py
linq/workflow.py
linq_sdk-1.11.0.dist-info/LICENSE
linq_sdk-1.11.0.dist-info/METADATA
linq_sdk-1.11.0.dist-info/WHEEL
linq_sdk-1.11.0.dist-info/entry_points.txt
linq_sdk-1.11.0.dist-info/RECORD
